collapse_gtdb_tree/__init__.py
collapse_gtdb_tree/__main__.py
collapse_gtdb_tree/_version.py
collapse_gtdb_tree/utils.py
collapse_gtdb_tree-0.0.3.dist-info/LICENSE
collapse_gtdb_tree-0.0.3.dist-info/METADATA
collapse_gtdb_tree-0.0.3.dist-info/WHEEL
collapse_gtdb_tree-0.0.3.dist-info/entry_points.txt
collapse_gtdb_tree-0.0.3.dist-info/top_level.txt
collapse_gtdb_tree-0.0.3.dist-info/RECORD
